{
    "_name": "Aya Blackpaw",
    "_effect": "Battlecry and Deathrattle: Summon a{1} {0} Jade Golem.",
    "Battlecry": {
        "targetType": "None",
        "effects": [
            {
                "type": "summon",
                "atk": 1,
                "hp": 1
            }
        ]
    },
    "Deathrattle": {
        "targetType": "None",
        "effects": [
            {
                "type": "summon",
                "atk": 1,
                "hp": 1
            }
        ]
    }
}
